sn_test/__init__.py
sn_test/test_sn.py
sn_test-1.0.4.dist-info/METADATA
sn_test-1.0.4.dist-info/WHEEL
sn_test-1.0.4.dist-info/top_level.txt
sn_test-1.0.4.dist-info/RECORD
