Metadata-Version: 2.1
Name: sn-test
Version: 1.0.4
Summary: shuainan test
Home-page: https://github.com/me/myproject
Author: shuainan
Author-email: 15294627382@163.com
License: MIT
Classifier: License :: OSI Approved :: MIT License
Classifier: Programming Language :: Python
Classifier: Programming Language :: Python :: 3
Classifier: Programming Language :: Python :: 3.6
Classifier: Programming Language :: Python :: Implementation :: CPython
Classifier: Programming Language :: Python :: Implementation :: PyPy
Requires-Python: >=3.6.0
Requires-Dist: requests
Requires-Dist: websocket
